tcp_h2_describe/__init__.py
tcp_h2_describe/__main__.py
tcp_h2_describe/_buffer.py
tcp_h2_describe/_connect.py
tcp_h2_describe/_describe.py
tcp_h2_describe/_display.py
tcp_h2_describe/_keepalive.py
tcp_h2_describe/_proxy_protocol.py
tcp_h2_describe/_serve.py
tcp_h2_describe-0.1.0.dist-info/LICENSE
tcp_h2_describe-0.1.0.dist-info/METADATA
tcp_h2_describe-0.1.0.dist-info/WHEEL
tcp_h2_describe-0.1.0.dist-info/entry_points.txt
tcp_h2_describe-0.1.0.dist-info/top_level.txt
tcp_h2_describe-0.1.0.dist-info/zip-safe
tcp_h2_describe-0.1.0.dist-info/RECORD
