Metadata-Version: 2.1
Name: tcp-h2-describe
Version: 0.1.0
Summary: Python library and CLI for running an HTTP/2 proxy that describes each frame
Home-page: https://github.com/dhermes/tcp-h2-describe
Author: Danny Hermes
Author-email: daniel.j.hermes@gmail.com
License: Apache 2.0
Project-URL: Issue Tracker, https://github.com/dhermes/tcp-h2-describe
Keywords: TCP,HTTP/2,Networking,Proxy
Platform: Posix; macOS; Windows
Classifier: License :: OSI Approved :: Apache Software License
Classifier: Operating System :: OS Independent
Classifier: Programming Language :: Python :: 3
Classifier: Programming Language :: Python :: 3.7
Requires-Dist: hpack (>=3.0.0)
